{
  "type": "function",
  "function": {
    "name": "semantic_search",
    "description": "Search documents based on conceptual similarity.",
    "long_description": "Searches documents by comparing overlapping terms between the user query and document content to approximate semantic similarity.",
    "domain": "Search & Information Retrieval",
    "parameters": {
      "type": "object",
      "properties": {
        "query": {
          "type": "string",
          "description": "Input parameter: query"
        },
        "corpus": {
          "type": "string",
          "description": "Input parameter: corpus"
        }
      },
      "required": [
        "query",
        "corpus"
      ]
    },
    "example_user_queries": [
      "Call semantic_search",
      "Execute semantic_search function",
      "Find content similar to timeout issues",
      "Find documents about authentication",
      "Find documents related to login issues",
      "Find reports discussing system issues",
      "How to use semantic_search?",
      "Invoke semantic_search.",
      "Look for files discussing failures",
      "Look up information about errors"
    ]
  }
}
