{
  "type": "function",
  "function": {
    "name": "get_weather_alerts_by_region",
    "description": "Get active weather alerts for a region.",
    "long_description": "Retrieves active weather warnings or alerts such as storms, heatwaves, or heavy rainfall for a specified region using an external weather API.",
    "domain": "General Utilities",
    "parameters": {
      "type": "object",
      "properties": {
        "region": {
          "type": "string",
          "description": "City, state, or region to check for weather alerts"
        }
      },
      "required": [
        "region"
      ]
    },
    "example_user_queries": [
      "Show active weather alerts for California.",
      "Are there any weather alerts in Texas?",
      "Get weather warnings for Kerala.",
      "Fetch current alerts for the Florida region.",
      "Tell me about weather alerts in New South Wales.",
      "Check severe weather warnings for Ontario.",
      "Show weather alerts for the Tokyo region.",
      "Get regional weather alerts for Maharashtra.",
      "What alerts are active in British Columbia?",
      "Fetch weather alerts using region Queensland."
    ]
  }
}
